ak_vendor/__init__.py
ak_vendor/admin.py
ak_vendor/apps.py
ak_vendor/blocklist.py
ak_vendor/compliances/__init__.py
ak_vendor/compliances/asvs.py
ak_vendor/compliances/cwe.py
ak_vendor/compliances/gdpr.py
ak_vendor/compliances/hipaa.py
ak_vendor/compliances/masvs.py
ak_vendor/compliances/mstg.py
ak_vendor/compliances/nistsp800171.py
ak_vendor/compliances/nistsp80053.py
ak_vendor/compliances/owasp.py
ak_vendor/compliances/owaspapi2023.py
ak_vendor/compliances/owaspmobile2024.py
ak_vendor/compliances/pcidss.py
ak_vendor/compliances/pcidss4.py
ak_vendor/compliances/sama.py
ak_vendor/constants.py
ak_vendor/enums.py
ak_vendor/locale/ja/LC_MESSAGES/django.mo
ak_vendor/locale/ja/LC_MESSAGES/django.po
ak_vendor/migrations/__init__.py
ak_vendor/models.py
ak_vendor/pnguncrush.py
ak_vendor/report/__init__.py
ak_vendor/report/report.py
ak_vendor/report_sample.py
ak_vendor/report_sample1.json
ak_vendor/seed.py
ak_vendor/templates/report_template.html
ak_vendor/translations/ja/vulnerability.xlsx
ak_vendor/utils.py
ak_vendor/views.py
ak_vendor-6.11.0.dist-info/LICENSE
ak_vendor-6.11.0.dist-info/METADATA
ak_vendor-6.11.0.dist-info/WHEEL
ak_vendor-6.11.0.dist-info/RECORD
