Metadata-Version: 2.3
Name: ak-vendor
Version: 6.11.0
Summary: Some vendor scripts that we use here at Appknox
License: MIT
Keywords: appknox,vendor
Author: Appknox
Author-email: engineering@appknox.com
Requires-Python: >=3.8,<4.0
Classifier: Intended Audience :: Developers
Classifier: License :: OSI Approved :: MIT License
Classifier: Operating System :: OS Independent
Classifier: Programming Language :: Python
Classifier: Programming Language :: Python :: 3
Classifier: Programming Language :: Python :: 3.8
Classifier: Programming Language :: Python :: 3.9
Classifier: Programming Language :: Python :: 3.10
Classifier: Programming Language :: Python :: 3.11
Classifier: Programming Language :: Python :: 3.12
Classifier: Programming Language :: Python :: 3.13
Classifier: Topic :: Software Development :: Build Tools
Requires-Dist: attrs (>=21.1.0)
Requires-Dist: cvss (>=2.0)
Requires-Dist: html2text (==2020.1.16)
Requires-Dist: orm-choices (==0.3.0)
Project-URL: Repository, https://github.com/appknox/vendor
